example/__example__.py
example/__init__.py
pifireeye/__init__.py
pifireeye/api_client.py
pifireeye/configuration.py
pifireeye/rest.py
pifireeye/api/__init__.py
pifireeye/api/category_api.py
pifireeye/api/dashboard_api.py
pifireeye/api/device_command_api.py
pifireeye/api/device_signal_api.py
pifireeye/api/device_status_api.py
pifireeye/api/error_info_api.py
pifireeye/api/image_api.py
pifireeye/api/order_api.py
pifireeye/api/platform_api.py
pifireeye/api/user_api.py
pifireeye/api/utils.py
pifireeye/example/__example__.py
pifireeye/example/__init__.py
pifireeye/models/__init__.py
pifireeye/models/dashboard2d_time_series_response.py
pifireeye/models/device_command.py
pifireeye/models/device_signal.py
pifireeye/models/device_status.py
pifireeye/models/error_info.py
pifireeye/models/image.py
pifireeye/models/image_category.py
pifireeye/models/order.py
pifireeye/models/order_category.py
pifireeye/models/platform.py
pifireeye/models/signal.py
pifireeye/models/task_category.py
pifireeye/models/task_latest_status.py
pifireeye/models/user_profile.py
pifireeye-1.1.4.dist-info/METADATA
pifireeye-1.1.4.dist-info/WHEEL
pifireeye-1.1.4.dist-info/top_level.txt
pifireeye-1.1.4.dist-info/RECORD
